[
  {
    "Id": "journey1",
    "Title": "Erkundung zu Fuß",
    "Message": "%STAT% zurückgelegt",
    "SingularMessage": "",
    "Stats": [
      {
        "LevelName": "Erste Schritte",
        "Value": 0
      },
      {
        "LevelName": "Aufbruch",
        "Value": 8000
      },
      {
        "LevelName": "Bummler",
        "Value": 10000
      },
      {
        "LevelName": "Umherziehend",
        "Value": 15000
      },
      {
        "LevelName": "Wanderer",
        "Value": 20000
      },
      {
        "LevelName": "Spaziergänger",
        "Value": 25000
      },
      {
        "LevelName": "Läufer",
        "Value": 30000
      },
      {
        "LevelName": "Nomad",
        "Value": 40000
      },
      {
        "LevelName": "Wanderin",
        "Value": 50000
      },
      {
        "LevelName": "Forschungsreisender",
        "Value": 75000
      },
      {
        "LevelName": "Abenteurerin",
        "Value": 100000
      }
    ]
  },
  {
    "Id": "journey2",
    "Title": "Alien-Begegnungen",
    "Message": "Aliens getroffen: %STAT%",
    "SingularMessage": "",
    "Stats": [
      {
        "LevelName": "Einsam",
        "Value": 0
      },
      {
        "LevelName": "Nicht allein",
        "Value": 10
      },
      {
        "LevelName": "Besucher",
        "Value": 20
      },
      {
        "LevelName": "Erkannt",
        "Value": 30
      },
      {
        "LevelName": "Vertraut",
        "Value": 35
      },
      {
        "LevelName": "Berühmt",
        "Value": 40
      },
      {
        "LevelName": "Emissär",
        "Value": 45
      },
      {
        "LevelName": "Diplomat",
        "Value": 50
      },
      {
        "LevelName": "Gesandter",
        "Value": 60
      },
      {
        "LevelName": "Konsul",
        "Value": 70
      },
      {
        "LevelName": "Botschafter",
        "Value": 80
      }
    ]
  },
  {
    "Id": "journey3",
    "Title": "Gesammelte Worte",
    "Message": "Worte gelernt: %STAT%",
    "SingularMessage": "",
    "Stats": [
      {
        "LevelName": "Schwätzer",
        "Value": 0
      },
      {
        "LevelName": "Anfänger",
        "Value": 5
      },
      {
        "LevelName": "Schüler",
        "Value": 8
      },
      {
        "LevelName": "Verständlich",
        "Value": 10
      },
      {
        "LevelName": "Gelehrter",
        "Value": 15
      },
      {
        "LevelName": "Fließend",
        "Value": 20
      },
      {
        "LevelName": "Übersetzer",
        "Value": 30
      },
      {
        "LevelName": "Linguist",
        "Value": 50
      },
      {
        "LevelName": "Polyglott",
        "Value": 80
      },
      {
        "LevelName": "Universalübersetzer",
        "Value": 100
      },
      {
        "LevelName": "Babelfisch",
        "Value": 150
      }
    ]
  },
  {
    "Id": "journey4",
    "Title": "Erhaltene Units",
    "Message": "%STAT% Units verdient",
    "SingularMessage": "",
    "Stats": [
      {
        "LevelName": "Neues Geschäft",
        "Value": 0
      },
      {
        "LevelName": "Weltraum-Trucker",
        "Value": 75000
      },
      {
        "LevelName": "Händler",
        "Value": 100000
      },
      {
        "LevelName": "Geldmacher",
        "Value": 150000
      },
      {
        "LevelName": "Kaufmann",
        "Value": 250000
      },
      {
        "LevelName": "Geschäftstüchtig",
        "Value": 500000
      },
      {
        "LevelName": "Entrepreneur",
        "Value": 750000
      },
      {
        "LevelName": "Investor",
        "Value": 1000000
      },
      {
        "LevelName": "Kapitalist",
        "Value": 1250000
      },
      {
        "LevelName": "Tycoon",
        "Value": 1500000
      },
      {
        "LevelName": "Magnat",
        "Value": 2000000
      }
    ]
  },
  {
    "Id": "journey5",
    "Title": "Zerstörte Schiffe",
    "Message": "Raumschiffe zerstört: %STAT%",
    "SingularMessage": "",
    "Stats": [
      {
        "LevelName": "Ungetestet",
        "Value": 0
      },
      {
        "LevelName": "Neuling",
        "Value": 5
      },
      {
        "LevelName": "Quälgeist",
        "Value": 10
      },
      {
        "LevelName": "Schrotthändler",
        "Value": 15
      },
      {
        "LevelName": "Störenfried",
        "Value": 20
      },
      {
        "LevelName": "Jäger",
        "Value": 30
      },
      {
        "LevelName": "Bedrohung",
        "Value": 40
      },
      {
        "LevelName": "Berüchtigte",
        "Value": 50
      },
      {
        "LevelName": "Gefährlich",
        "Value": 60
      },
      {
        "LevelName": "Experte",
        "Value": 70
      },
      {
        "LevelName": "Legende",
        "Value": 80
      }
    ]
  },
  {
    "Id": "journey6",
    "Title": "Wächter zerstört",
    "Message": "%STAT% Wächter zerstört",
    "SingularMessage": "",
    "Stats": [
      {
        "LevelName": "Ungestört",
        "Value": 0
      },
      {
        "LevelName": "Neuling",
        "Value": 5
      },
      {
        "LevelName": "Gezielte Anomalie",
        "Value": 10
      },
      {
        "LevelName": "Verhärtet",
        "Value": 15
      },
      {
        "LevelName": "Radikale",
        "Value": 20
      },
      {
        "LevelName": "Berufen durch Feuer",
        "Value": 30
      },
      {
        "LevelName": "Unsterblich",
        "Value": 40
      },
      {
        "LevelName": "Heldin",
        "Value": 50
      },
      {
        "LevelName": "Kreuzfahrer",
        "Value": 60
      },
      {
        "LevelName": "Läuterer der Welten",
        "Value": 70
      },
      {
        "LevelName": "Glaszerstörer",
        "Value": 80
      }
    ]
  },
  {
    "Id": "journey7",
    "Title": "Extremes Überleben",
    "Message": "%STAT% überlebt",
    "SingularMessage": "",
    "Stats": [
      {
        "LevelName": "Hoffnungsvoll",
        "Value": 0
      },
      {
        "LevelName": "Todesmutig",
        "Value": 900
      },
      {
        "LevelName": "Resolut",
        "Value": 2700
      },
      {
        "LevelName": "Entschlossen",
        "Value": 4500
      },
      {
        "LevelName": "begeistert",
        "Value": 8000
      },
      {
        "LevelName": "Hartnäckig",
        "Value": 12960
      },
      {
        "LevelName": "Zerklüftet",
        "Value": 18720
      },
      {
        "LevelName": "Robust",
        "Value": 27000
      },
      {
        "LevelName": "Unermüdlich",
        "Value": 32400
      },
      {
        "LevelName": "Überlebenskämpfer",
        "Value": 37800
      },
      {
        "LevelName": "Immerwährende",
        "Value": 43200
      }
    ]
  },
  {
    "Id": "journey8",
    "Title": "Weltraumerkundung",
    "Message": "%STAT% Mal gewarpt",
    "SingularMessage": "",
    "Stats": [
      {
        "LevelName": "Sternengucker",
        "Value": 0
      },
      {
        "LevelName": "Vorreiterin",
        "Value": 5
      },
      {
        "LevelName": "Kundschafter",
        "Value": 10
      },
      {
        "LevelName": "Warp-aktiviert",
        "Value": 15
      },
      {
        "LevelName": "Gutachterin",
        "Value": 20
      },
      {
        "LevelName": "Vagabund",
        "Value": 25
      },
      {
        "LevelName": "Reisende",
        "Value": 30
      },
      {
        "LevelName": "Pionier",
        "Value": 40
      },
      {
        "LevelName": "Entdecker",
        "Value": 50
      },
      {
        "LevelName": "Aufseher",
        "Value": 60
      },
      {
        "LevelName": "Entdecker",
        "Value": 75
      }
    ]
  },
  {
    "Id": "journey9",
    "Title": "Planeten-Zoologie",
    "Message": "Alle Spezies auf %STAT% Planeten entdeckt",
    "SingularMessage": "",
    "Stats": [
      {
        "LevelName": "Amateur",
        "Value": 0
      },
      {
        "LevelName": "Naturforscher",
        "Value": 1
      },
      {
        "LevelName": "Sammler",
        "Value": 2
      },
      {
        "LevelName": "Scanner",
        "Value": 3
      },
      {
        "LevelName": "Analyst",
        "Value": 4
      },
      {
        "LevelName": "Forscher",
        "Value": 5
      },
      {
        "LevelName": "Datensammler",
        "Value": 6
      },
      {
        "LevelName": "Archivar",
        "Value": 7
      },
      {
        "LevelName": "Klassifizierer",
        "Value": 8
      },
      {
        "LevelName": "Zoologe",
        "Value": 9
      },
      {
        "LevelName": "Enzyklopädie",
        "Value": 10
      }
    ]
  }
]